calculator_mega99/__init__.py
calculator_mega99/calculator.py
calculator_mega99-0.0.5.dist-info/METADATA
calculator_mega99-0.0.5.dist-info/WHEEL
calculator_mega99-0.0.5.dist-info/licenses/LICENSE
calculator_mega99-0.0.5.dist-info/RECORD
