Metadata-Version: 2.1
Name: calculator_mega99
Version: 0.0.5
Summary: A small example package
Project-URL: Homepage, https://github.com/AB314159/calculator_mega99
Project-URL: Bug Tracker, https://github.com/AB314159/calculator_mega99/issues
Author-email: AB314159 <aryajb2013@gmail.com>
License: Copyright (c) 2022 owner of acodingwebsite.w3spaces.com
License-File: LICENSE
Classifier: License :: OSI Approved :: MIT License
Classifier: Operating System :: OS Independent
Classifier: Programming Language :: Python :: 3
Requires-Python: >=3.7
